izpy/__init__.py
izpy/errors.py
izpy/requests.py
izpy-0.0.6.dist-info/LICENSE
izpy-0.0.6.dist-info/METADATA
izpy-0.0.6.dist-info/WHEEL
izpy-0.0.6.dist-info/top_level.txt
izpy-0.0.6.dist-info/zip-safe
izpy-0.0.6.dist-info/RECORD
