Metadata-Version: 2.1
Name: izpy
Version: 0.0.6
Summary: AbstractTest class for generic calls in integration testing of API's
Home-page: https://github.com/MissHead/izpy
Author: Izabela Ramos Ferreira
Author-email: izabela.head@gmail.com
License: GNU GENERAL PUBLIC LICENSE
Keywords: generic calls,curl,errors
Platform: UNKNOWN
Requires-Python: >=3.6
